Mod8Counter.v
module Mod8Counter (
	input clk,    // Clock
	input clr,  // Asynchronous clear
	output [2:0]Q
);

reg [2:0]Q;

always @(posedge clk or negedge clr) 
begin 
	if(~clr) 
	begin
		Q <= 3'b000;
	end 
	else 
	begin
		Q <= Q + 1;
	end
end

endmodule

Mod8Counter_tb.v
`timescale 1s/100ms
`include "Mod8Counter.v"

module Mod8Counter_tb ();

	reg clk;
	reg clr;
	wire [2:0]Q;

	Mod8Counter myCounter(clk, clr, Q);

	initial
	begin 
		$monitor("Count = %4b", Q);
		$dumpfile("mod8Counter.vcd");
		$dumpvars(0, Mod8Counter_tb);

		clr <= 0;
		clk <= 1; #1;
		clr <= 1;
		clk <= 0; #1;

		clk <= 1; #1;
		clk <= 0; #1; //Count 1

		clk <= 1; #1;
		clk <= 0; #1; //Count 2

		clk <= 1; #1;
		clk <= 0; #1; //Count 3

		clk <= 1; #1;
		clk <= 0; #1; //Count 4

		clk <= 1; #1;
		clk <= 0; #1; //Count 5

		clk <= 1; #1;
		clk <= 0; #1; //Count 6

		clk <= 1; #1;
		clk <= 0; #1; //Count 7

		clk <= 1; #1;
		clk <= 0; #1; //Count 8

		clk <= 1; #1;
		clk <= 0; #1; //Count 1

		clk <= 1; #1;
		clk <= 0; #1;//Count 2

		clr <= 0;
		clk <= 1; #1;
		clr <= 1;
		clk <= 0; #1;

		clk <= 1; #1;
		clk <= 0; #1; //Count 1

		clk <= 1; #1;
		clk <= 0; #1; //Count 2

		$finish;
	end

endmodule

mod8Counter.vcd
$date
	Mon Nov 12 23:06:51 2018
$end
$version
	Icarus Verilog
$end
$timescale
	100ms
$end
$scope module Mod8Counter_tb $end
$var wire 3 ! Q [2:0] $end
$var reg 1 " clk $end
$var reg 1 # clr $end
$scope module myCounter $end
$var wire 1 " clk $end
$var wire 1 # clr $end
$var reg 3 $ Q [2:0] $end
$upscope $end
$upscope $end
$enddefinitions $end
#0
$dumpvars
b0 $
0#
1"
b0 !
$end
#10
0"
1#
#20
b1 !
b1 $
1"
#30
0"
#40
b10 !
b10 $
1"
#50
0"
#60
b11 !
b11 $
1"
#70
0"
#80
b100 !
b100 $
1"
#90
0"
#100
b101 !
b101 $
1"
#110
0"
#120
b110 !
b110 $
1"
#130
0"
#140
b111 !
b111 $
1"
#150
0"
#160
b0 !
b0 $
1"
#170
0"
#180
b1 !
b1 $
1"
#190
0"
#200
b10 !
b10 $
1"
#210
0"
#220
b0 !
b0 $
1"
0#
#230
0"
1#
#240
b1 !
b1 $
1"
#250
0"
#260
b10 !
b10 $
1"
